com/__init__.py
com/johnsnowlabs/__init__.py
com/johnsnowlabs/nlp/__init__.py
sparknlp/__init__.py
sparknlp/annotation.py
sparknlp/annotation_audio.py
sparknlp/annotation_image.py
sparknlp/functions.py
sparknlp/upload_to_hub.py
sparknlp/util.py
sparknlp/annotator/__init__.py
sparknlp/annotator/chunker.py
sparknlp/annotator/document_normalizer.py
sparknlp/annotator/graph_extraction.py
sparknlp/annotator/lemmatizer.py
sparknlp/annotator/n_gram_generator.py
sparknlp/annotator/normalizer.py
sparknlp/annotator/stemmer.py
sparknlp/annotator/stop_words_cleaner.py
sparknlp/annotator/tf_ner_dl_graph_builder.py
sparknlp/annotator/audio/__init__.py
sparknlp/annotator/audio/wav2vec2_for_ctc.py
sparknlp/annotator/classifier_dl/__init__.py
sparknlp/annotator/classifier_dl/albert_for_question_answering.py
sparknlp/annotator/classifier_dl/albert_for_sequence_classification.py
sparknlp/annotator/classifier_dl/albert_for_token_classification.py
sparknlp/annotator/classifier_dl/bert_for_question_answering.py
sparknlp/annotator/classifier_dl/bert_for_sequence_classification.py
sparknlp/annotator/classifier_dl/bert_for_token_classification.py
sparknlp/annotator/classifier_dl/camembert_for_sequence_classification.py
sparknlp/annotator/classifier_dl/camembert_for_token_classification.py
sparknlp/annotator/classifier_dl/classifier_dl.py
sparknlp/annotator/classifier_dl/deberta_for_question_answering.py
sparknlp/annotator/classifier_dl/deberta_for_sequence_classification.py
sparknlp/annotator/classifier_dl/deberta_for_token_classification.py
sparknlp/annotator/classifier_dl/distil_bert_for_question_answering.py
sparknlp/annotator/classifier_dl/distil_bert_for_sequence_classification.py
sparknlp/annotator/classifier_dl/distil_bert_for_token_classification.py
sparknlp/annotator/classifier_dl/longformer_for_question_answering.py
sparknlp/annotator/classifier_dl/longformer_for_sequence_classification.py
sparknlp/annotator/classifier_dl/longformer_for_token_classification.py
ckls_test_lib-4.2.7.dist-info/METADATA
ckls_test_lib-4.2.7.dist-info/WHEEL
ckls_test_lib-4.2.7.dist-info/top_level.txt
ckls_test_lib-4.2.7.dist-info/RECORD
